bin2hex/__init__.py
bin2hex/__main__.py
bin2hex/bin2c.py
bin2hex/bin2model.py
bin2hex/bin2verilog.py
bin2hex/ecc.py
bin2hex/main.py
bin2hex-2.2.0.dist-info/licenses/LICENSE
bin2hex-2.2.0.dist-info/METADATA
bin2hex-2.2.0.dist-info/WHEEL
bin2hex-2.2.0.dist-info/entry_points.txt
bin2hex-2.2.0.dist-info/top_level.txt
bin2hex-2.2.0.dist-info/RECORD
