Metadata-Version: 2.4
Name: bin2hex
Version: 2.2.0
Summary: bin2hex is an utility to convert binary file to multiple types of hexadecimal text file
Author-email: Yitao Zhang <xtayyt@gmail.com>
License-Expression: BSD-3-Clause
Project-URL: Homepage, https://github.com/xtayyt/bin2hex
Project-URL: Repository, https://github.com/xtayyt/bin2hex.git
Project-URL: Issues, https://github.com/xtayyt/bin2hex/issues
Project-URL: Changelog, https://github.com/xtayyt/bin2hex/blob/master/CHANGELOG.md
Keywords: bin2hex,bin2vhx,binary,bin,hexadecimal,hex,vhx,denali,verilog,convert
Classifier: Programming Language :: Python
Classifier: Operating System :: OS Independent
Classifier: Development Status :: 3 - Alpha
Classifier: Topic :: Scientific/Engineering :: Electronic Design Automation (EDA)
Classifier: Topic :: Software Development :: Embedded Systems
Classifier: Topic :: Utilities
Requires-Python: >=3.8
License-File: LICENSE
Dynamic: license-file
